gradio_vistimeline/__init__.py
gradio_vistimeline/model.py
gradio_vistimeline/vistimeline.py
gradio_vistimeline/vistimeline.pyi
gradio_vistimeline/templates/component/index.js
gradio_vistimeline/templates/component/style.css
gradio_vistimeline/templates/example/index.js
gradio_vistimeline/templates/example/style.css
gradio_vistimeline-1.0.1.dist-info/METADATA
gradio_vistimeline-1.0.1.dist-info/WHEEL
gradio_vistimeline-1.0.1.dist-info/RECORD
